{"cameraMode":{"drawMode":0,"name":"Shaded","section":"Shading Mode"},"sceneLighting":true,"audioPlay":false,"sceneViewState":{"showFog":true,"showMaterialUpdate":false,"showSkybox":true,"showFlares":true,"showImageEffects":true,"showParticleSystems":true},"in2DMode":false,"pivot":{"x":-10.86492919921875,"y":2.5604701042175295,"z":70.93160247802735},"rotation":{"x":-0.06625588238239289,"y":0.39765962958335879,"z":-0.028805628418922426,"w":-0.9146916270256043},"size":36.39921951293945,"orthographic":false}